requestsa/__init__.py
requestsa/__version__.py
requestsa/_internal_utils.py
requestsa/adapters.py
requestsa/api.py
requestsa/auth.py
requestsa/certs.py
requestsa/compat.py
requestsa/cookies.py
requestsa/exceptions.py
requestsa/help.py
requestsa/hooks.py
requestsa/models.py
requestsa/packages.py
requestsa/sessions.py
requestsa/status_codes.py
requestsa/structures.py
requestsa/utils.py
requestsa/write.py
requestsabc_001A-0.0.3.dist-info/METADATA
requestsabc_001A-0.0.3.dist-info/WHEEL
requestsabc_001A-0.0.3.dist-info/top_level.txt
requestsabc_001A-0.0.3.dist-info/RECORD
