Metadata-Version: 2.1
Name: requestsabc-001A
Version: 0.0.3
Summary: 简单的加减运算上传测试
Home-page: https://www.baidu.com
Author: 布诺妮亚
Author-email: 123@baka.com
Classifier: Programming Language :: Python :: 3
Classifier: License :: OSI Approved :: MIT License
Classifier: Operating System :: OS Independent
